randextract/__init__.py
randextract/_verify.py
randextract/polynomial_hashing.py
randextract/randomness_extractor.py
randextract/toeplitz_hashing.py
randextract/trevisan_extractor.py
randextract/validator.py
randextract/validator_custom_class.py
randextract/xor_one_bit_extractor.py
randextract/trevisan/__init__.py
randextract/trevisan/block_design.py
randextract/trevisan/finite_field_polynomial_design.py
randextract/trevisan/weak_design.py
randextract/utilities/__init__.py
randextract/utilities/binary_entropy.py
randextract/utilities/converter.py
randextract-0.2.2.dist-info/licenses/LICENSE
randextract-0.2.2.dist-info/METADATA
randextract-0.2.2.dist-info/WHEEL
randextract-0.2.2.dist-info/top_level.txt
randextract-0.2.2.dist-info/RECORD
