Metadata-Version: 2.4
Name: randextract
Version: 0.2.2
Summary: A reference implementation for testing & validating Privacy Amplification algorithms
Author-email: Esther Hänggi <esther.haenggi@hslu.ch>, Iyán Méndez Veiga <iyan.mendezveiga@hslu.ch>
License-Expression: MIT
Project-URL: Homepage, https://randextract.crypto-lab.ch
Project-URL: Issues, https://github.com/cryptolab/randextract/issues
Keywords: Quantum Cryptography,Randomness Extractor,Privacy Amplification
Classifier: Programming Language :: Python :: 3
Classifier: Operating System :: OS Independent
Requires-Python: <3.14,>=3.10
License-File: LICENSE
Requires-Dist: numpy>=1.21.0
Requires-Dist: galois>=0.3.6
Requires-Dist: scipy>=1.12
Requires-Dist: gmpy2<3,>=2.2.0a1
Requires-Dist: termcolor>=2.4
Provides-Extra: dev
Requires-Dist: black; extra == "dev"
Requires-Dist: build; extra == "dev"
Requires-Dist: isort; extra == "dev"
Requires-Dist: jupyterlab; extra == "dev"
Requires-Dist: matplotlib; extra == "dev"
Requires-Dist: twine; extra == "dev"
Provides-Extra: docs
Requires-Dist: Sphinx; extra == "docs"
Requires-Dist: sphinx-book-theme; extra == "docs"
Requires-Dist: sphinxcontrib-bibtex; extra == "docs"
Requires-Dist: sphinx-togglebutton; extra == "docs"
Requires-Dist: sphinx-tabs; extra == "docs"
Requires-Dist: sphinx-autodoc-typehints; extra == "docs"
Provides-Extra: examples
Requires-Dist: pyzmq; extra == "examples"
Provides-Extra: test
Requires-Dist: pytest; extra == "test"
Requires-Dist: pytest-cov; extra == "test"
Provides-Extra: all
Requires-Dist: randextract[dev,docs,examples,test]; extra == "all"
Dynamic: license-file
